{
  "name": "book.adorablehamsterpets.entry.haute_couture",
  "icon": "minecraft:pink_petals",
  "category": "adorablehamsterpets:accessories",
  "entry_color": "00AAAA",
  "sortnum": 0,
  "pages": [
    {
      "type": "adorablehamsterpets:page",
      "header": "book.adorablehamsterpets.entry.haute_couture",
      "header_color": "00AAAA",
      "text_color": "000000",
      "text": "book.adorablehamsterpets.entry.haute_couture.page1.body"
    },
    {
      "type": "patchouli:entity",
      "entity": "adorablehamsterpets:hamster{PinkPetalType: 3, HamsterVariant: 1}",
      "default_rotation": 55,
      "scale": 1.2,
      "rotate" : false,
      "name": "Hamster",
      "text": "Maybe change to the image instead?"
    },
    {
      "type": "patchouli:text",
      "text": "book.adorablehamsterpets.entry.haute_couture.page3.body"
    },
    {
      "type": "patchouli:link",
      "url": "https://discord.gg/w54mk5bqdf",
      "link_text": "book.adorablehamsterpets.entry.haute_couture.page4.link_text",
      "text": "book.adorablehamsterpets.entry.haute_couture.page4.body"
    }
  ]
}